{
  "project_info": {
    "project_number": "200007204776",
    "project_id": "glossong-30165",
    "storage_bucket": "glossong-30165.appspot.com"
  },
  "client": [
    {
      "client_info": {
        "mobilesdk_app_id": "1:200007204776:android:6b949a82c51fc5d4b7279d",
        "android_client_info": {
          "package_name": "com.example.glossong"
        }
      },
      "oauth_client": [
        {
          "client_id": "200007204776-l04huokvq6cq0t8npeiumvru0mnbui93.apps.googleusercontent.com",
          "client_type": 3
        }
      ],
      "api_key": [
        {
          "current_key": "AIzaSyCwv5BqwBFQUsPyD2X_pwgF0Ip26VWuALM"
        }
      ],
      "services": {
        "appinvite_service": {
          "other_platform_oauth_client": [
            {
              "client_id": "200007204776-l04huokvq6cq0t8npeiumvru0mnbui93.apps.googleusercontent.com",
              "client_type": 3
            }
          ]
        }
      }
    }
  ],
  "configuration_version": "1"
}